hubble/__init__.py
hubble/config.py
hubble/keys.py
hubble/shell.py
hubble-1.1.6.dist-info/DESCRIPTION.rst
hubble-1.1.6.dist-info/METADATA
hubble-1.1.6.dist-info/RECORD
hubble-1.1.6.dist-info/WHEEL
hubble-1.1.6.dist-info/entry_points.txt
hubble-1.1.6.dist-info/metadata.json
hubble-1.1.6.dist-info/pbr.json
hubble-1.1.6.dist-info/top_level.txt
