Metadata-Version: 2.0
Name: hubble
Version: 1.1.6
Summary: Hubble is an environment variable manager for tools like cinderclient, novaclient, swiftclient and swiftly and others!
Home-page: https://github.com/thrawn01/hubble
Author: Derrick J. Wippler
Author-email: thrawn01@gmail.com
License: UNKNOWN
Platform: UNKNOWN
Classifier: Development Status :: 5 - Production/Stable
Classifier: Environment :: Console
Classifier: Intended Audience :: Information Technology
Classifier: Intended Audience :: System Administrators
Classifier: License :: OSI Approved :: Apache Software License
Classifier: Operating System :: POSIX :: Linux
Classifier: Programming Language :: Python
Classifier: Programming Language :: Python :: 2
Classifier: Programming Language :: Python :: 2.6
Classifier: Programming Language :: Python :: 2.7
Requires-Dist: keyring (>=5.0)
